sphinxext/opengraph/__init__.py
sphinxext/opengraph/_description_parser.py
sphinxext/opengraph/_meta_parser.py
sphinxext/opengraph/_social_cards.py
sphinxext/opengraph/_title_parser.py
sphinxext/opengraph/_static/Roboto-Flex.ttf
sphinxext/opengraph/_static/sphinx-logo-shadow.png
sphinxext_opengraph-0.12.0.dist-info/licenses/LICENCE.rst
sphinxext_opengraph-0.12.0.dist-info/WHEEL
sphinxext_opengraph-0.12.0.dist-info/METADATA
sphinxext_opengraph-0.12.0.dist-info/RECORD
