Metadata-Version: 2.4
Name: sphinxext-opengraph
Version: 0.12.0
Summary: Sphinx Extension to enable OGP support
Author-email: Itay Ziv <itay220204@gmail.com>
Requires-Python: >=3.9
License-Expression: BSD-3-Clause
Classifier: Development Status :: 5 - Production/Stable
Classifier: Environment :: Plugins
Classifier: Environment :: Web Environment
Classifier: Framework :: Sphinx :: Extension
Classifier: Intended Audience :: Developers
Classifier: Natural Language :: English
Classifier: Operating System :: OS Independent
Classifier: Programming Language :: Python :: 3.9
Classifier: Programming Language :: Python :: 3.10
Classifier: Programming Language :: Python :: 3.11
Classifier: Programming Language :: Python :: 3.12
Classifier: Programming Language :: Python :: 3.13
Classifier: Programming Language :: Python :: 3.14
Classifier: Programming Language :: Python
Classifier: Topic :: Documentation :: Sphinx
Classifier: Topic :: Documentation
Classifier: Topic :: Software Development :: Documentation
Classifier: Topic :: Text Processing
Classifier: Topic :: Utilities
License-File: LICENCE.rst
Requires-Dist: Sphinx>=6.0
Requires-Dist: furo>=2024 ; extra == "rtd"
Requires-Dist: sphinx-design ; extra == "rtd"
Requires-Dist: sphinx~=8.1.0 ; extra == "rtd"
Requires-Dist: matplotlib>=3 ; extra == "social-cards"
Project-URL: Code, https://github.com/sphinx-doc/sphinxext-opengraph/
Project-URL: Documentation, https://sphinxext-opengraph.readthedocs.io/
Project-URL: Download, https://pypi.org/project/sphinxext-opengraph/
Project-URL: Homepage, https://github.com/sphinx-doc/sphinxext-opengraph/
Project-URL: Issue tracker, https://github.com/sphinx-doc/sphinxext-opengraph/issues
Provides-Extra: rtd
Provides-Extra: social-cards
